{
	"SmuttureINaturen": {
		"heading": "Smutture-i-naturen",

		"house": [
			{
				"images": [
					"airbnb-image1.jpeg",
					"airbnb-image2.jpeg",
					"airbnb-image3.jpeg",
					"airbnb-image4.jpeg",
					"airbnb-image5.jpeg",
					"super-host.jpeg"
				],

				"info": {
					"mainInfo": "Architectural vacation house exotic courtyard",
					"subInfo": "Hel(t) hytte i kirke Hyllinge"
				},
				"gæster": 4,
				"studioLejhed": 1,
				"senge": 4,
				"bad": 1.5,
				"liked": true,
				"stars": 4.94,
				"views": 16,
				"location": {
					"country": "Denmark",
					"city": "Farsø"
				},
				"host": {
					"superhost": true,
					"name": "Dejene",
					"month": "january",
					"year": 2016
				},
				"tilbud": ["køkken", " Pejs", "Husdyr tilladt", "Husdyr tilladt"]
			},
			{
				"images": [
					"airbnb-second-catagory.jpeg",
					"airbnb-second-catagory1.jpeg",
					"airbnb-second-catagory2.jpeg",
					"airbnb-second-catagory3.jpeg",
					"airbnb-second-catagory4.jpeg",
					"super-host.jpeg"
				],

				"info": {
					"mainInfo": "Architectural vacation house exotic courtyard",
					"subInfo": "Hel(t) hytte i kirke Hyllinge"
				},
				"gæster": 4,
				"studioLejhed": 1,
				"senge": 4,
				"bad": 1.5,
				"liked": true,
				"stars": 4.94,
				"views": 16,
				"location": {
					"country": "Denmark",
					"city": "Farsø"
				},
				"host": {
					"superhost": false,
					"name": "Dejene",
					"month": "january",
					"year": 2016
				},
				"tilbud": ["køkken", " Pejs", "Husdyr tilladt", "Husdyr tilladt"]
			},
			{
				"images": [
					"airbnb-third-catagory.jpeg",
					"airbnb-third-catagory1.jpeg",
					"airbnb-third-catagory2.jpeg",
					"airbnb-third-catagory3.jpeg",
					"airbnb-third-catagory4.jpeg",
					"super-host.jpeg"
				],

				"info": {
					"mainInfo": "Architectural vacation house exotic courtyard",
					"subInfo": "Hel(t) hytte i kirke Hyllinge"
				},
				"gæster": 4,
				"studioLejhed": 1,
				"senge": 4,
				"bad": 1.5,
				"liked": true,
				"stars": 4.94,
				"views": 16,
				"location": {
					"country": "Denmark",
					"city": "Farsø"
				},
				"host": {
					"superhost": false,
					"name": "Dejene",
					"month": "january",
					"year": 2016
				},
				"tilbud": ["køkken", " Pejs", "Husdyr tilladt", "Husdyr tilladt"]
			}
		]
	}
}
